ralf_dialogue/__init__.py
ralf_dialogue/conversation.py
ralf_dialogue/dialogue.py
ralf_dialogue/planners.py
ralf_dialogue/services.py
ralf_dialogue/world_state.py
ralf_dialogue/ralf_data/models.yml
ralf_dialogue/ralf_data/prompts.yml
ralf_dialogue_jhuapl-0.0.4.dist-info/LICENSE
ralf_dialogue_jhuapl-0.0.4.dist-info/WHEEL
ralf_dialogue_jhuapl-0.0.4.dist-info/METADATA
ralf_dialogue_jhuapl-0.0.4.dist-info/RECORD
