Metadata-Version: 2.1
Name: ralf-dialogue-jhuapl
Version: 0.0.4
Summary: An extension of the ralf toolkit with convenient primitives for building LLM-based dialogue agents.
Author-email: JHUAPL <ralf@jhuapl.edu>
Requires-Python: >=3.9
Classifier: Programming Language :: Python :: 3
Classifier: Operating System :: OS Independent
Classifier: License :: OSI Approved :: MIT License
Requires-Dist: ralf-jhuapl
Requires-Dist: termcolor
Project-URL: Documentation, https://ralf-test.readthedocs.io/en/latest/
Project-URL: Source, https://github.com/jhuapl-fomo/ralf-dialogue
